{
  "id" : "0001999900000000233300197800000050000",
  "title" : "REFUND. LADEBETRAG",
  "subtitle" : "",
  "sender" : null,
  "senderName" : null,
  "senderOriginator" : null,
  "senderReference" : null,
  "receiver" : null,
  "receiverName" : null,
  "receiverReference" : null,
  "creditorId" : null,
  "amount" : {
    "value" : -700,
    "precision" : 2,
    "currency" : "EUR"
  },
  "amountSender" : {
    "value" : 0,
    "precision" : 2,
    "currency" : "EUR"
  },
  "amountAccounting" : null,
  "bookingDate" : 1475704800000,
  "valuationDate" : 1475704800000,
  "importDate" : 1486664261198,
  "inputDate" : null,
  "dueDate" : null,
  "exchangeDate" : null,
  "insertTimestamp" : 1475742913000,
  "reference" : null,
  "originatorSystem" : "MONEY2PAY",
  "additionalTexts" : {
    "text1" : null,
    "text2" : null,
    "text3" : null,
    "lineItems" : [ "REFUND. LADEBETRAG" ],
    "constantSymbol" : null,
    "variableSymbol" : null,
    "specificSymbol" : null
  },
  "note" : null,
  "bookingType" : "M2P-0724",
  "bookingTypeTranslation" : null,
  "orderRole" : "SENDER",
  "flags" : [ "IS_VISIBLE", "IS_BAL_RELEVANT", "THIRD_PARTY" ],
  "cardId" : "5NJCMB3AE",
  "maskedCardNumber" : "404856XXXXXX6431",
  "invoiceId" : null,
  "transactionDate" : 1475704800000,
  "location" : null,
  "foreignExchangeFee" : null,
  "transactionFee" : null,
  "exchangeRateValue" : 0,
  "exchangeRatePrecision" : 7,
  "cardType" : "main",
  "mcc" : "6010",
  "country" : "AT",
  "paymentType" : null,
  "cardCashbackAmount" : null,
  "cardBrand" : null,
  "merchantName" : null,
  "partnerName" : null,
  "partnerOriginator" : null,
  "partner" : null,
  "partnerData" : null,
  "logo" : {
    "id" : null,
    "uri" : "icon:ico-pfm-withdrawal"
  },
  "owner" : "000000002333",
  "balance" : null,
  "txType" : "PREPAIDCARD",
  "txDirection" : "OUTGOING",
  "cardInfo" : null,
  "atmData" : null,
  "posData" : null,
  "tags" : [ ],
  "attachment" : null,
  "saving" : null,
  "additionalData" : {
    "customerId" : null,
    "tags" : null,
    "marked" : false
  },
  "categories" : [ {
    "mainCategory" : "WITHDRAWAL",
    "subCategory" : "CREDIT_CARD_WITHDRAWAL",
    "amount" : {
      "value" : -700,
      "precision" : 2,
      "currency" : "EUR"
    },
    "hidden" : false
  } ],
  "categorizationSource" : {
    "type" : "GLOBAL_RULE",
    "content" : "{\n  \"merchantCode\" : \"6010\",\n  \"hidden\" : false,\n  \"subCategory\" : \"CREDIT_CARD_WITHDRAWAL\"\n}"
  },
  "paymentReference" : "REFUND. LADEBETRAG",
  "similarityKey" : "8A8E037A23ADA741FEF5ACA2F9FB15B1",
  "taxPayments" : null,
  "mandateId" : null,
  "sepaRecurrence" : null,
  "sepaScheme" : null,
  "mandateDate" : null,
  "fee" : null
}